Workbook

Sheet Cover
A10: (Project 224008)
A12: VOLUME IV
A14: BOQ
B47: Rev. T00 - Issued for Tender- 23rd September 2024

Sheet BILL 1 TO 14
A1: Item | B1: Description of Works | C1: Unit | D1: QTY | E1: RATE ( AED ) | F1: TOTAL Item PRICE ( AED )
B3: BILL NO. 1 : PRELIMINARIES
B4: These General Requirements are applicable to the whole of the works each item, clause or sub-clause must be individually priced. The Tenderer shall not enter any lump-sums covering more than one or all items, clauses or sub-clauses. Note: Where any item, clause, or sub clause of the preliminaries has not been priced, it will be deemed that the value of such item, clause or sub clause is included in the rates for measured items elsewhere in the bills of quantities. Any Work not specified in drawings, specification, BOQ but required as per local authorities and necessary to complete work to be included in the Main Contractors scope of work.
A5: 1.01 | B5: Provide site compound, workshops, secure storage areas, temporary external lighting, plant, roads, car shed ,etc. and remove on completion, including that for all Nominated Sub-Contractors | C5: Item | F5: =IFERROR(E5*D5,0) -> 0
A6: 1.02 | B6: Allow for any extreme physical constraints of the site | C6: Item | F6: =IFERROR(E6*D6,0) -> 0
A7: 1.03 | B7: Allow for protecting all the Works from the weather, damage, theft, including that of all Nominated Sub- Contractors and clearing away same on completion | C7: Item | F7: =IFERROR(E7*D7,0) -> 0
A8: 1.04 | B8: Allow for protecting all finished Work, including that of all Nominated Sub-Contractors, from damage however caused and theft | C8: Item | F8: =IFERROR(E8*D8,0) -> 0
A9: 1.05 | B9: Allow for temporary covering to excavations and other hazards | C9: Item | F9: =IFERROR(E9*D9,0) -> 0
A10: 1.06 | B10: Allow for temporary barricading to excavations, structural openings, shafts, exposed floor ends, roofs and all other hazards, etc. | C10: Item | F10: =IFERROR(E10*D10,0) -> 0
A11: 1.07 | B11: Allow for keeping the Site, roads, footpaths and any adjacent areas affected by the Works clear of debris and other rubbish during the progress of the Work and on completion | C11: Item | F11: =IFERROR(E11*D11,0) -> 0
A12: 1.08 | B12: Allow for site administration, Contractor Staff Sallaries, Overhead, Profits, supervision, security, safety, pest control, health and overtime (including any overtime requirements for the Engineer Representatives) | C12: Item | F12: =IFERROR(E12*D12,0) -> 0
A13: 1.09 | B13: Allow for hoarding and fencing requirements including regular maintenance and decoration with all gates and access and egress points, including removal on completion | C13: Item | F13: =IFERROR(E13*D13,0) -> 0
A14: 1.1 | B14: Allow for protecting adjacent roads and footpaths, working areas, etc. from falling debris, etc. from overhead works, including safety protection fans for all elevations, at all levels, including relocation to suit the course of the works | C14: Item | F14: =IFERROR(E14*D14,0) -> 0
A15: 1.11 | B15: Allow for providing plant and tools | C15: Item | F15: =IFERROR(E15*D15,0) -> 0
A16: 1.12 | B16: Allow for providing all scaffolding and cradles and maintaining with regular servicing and checks (including for all Nominated Sub-Contractors requirements) | C16: Item | F16: =IFERROR(E16*D16,0) -> 0
... A38: 1.34 | B38: Allow for including and considering (at the time of tendering and signing Contract agreement ) federal corporate tax on business profits applicable and imposed by UAE Government effective since June 2023. | C38: Item | F38: =IFERROR(E38*D38,0) -> 0
B39: Additional Items: The contractor to detail below any additional Items (with quantities and rates) shown in the drawings, mentioned in the specs. And /or required for satisfactory completion of the buildup of the lump sum project price of this section of works. Should the contractor fail to insert any Item in this section, it will be deemed that his lump sum price for the entire project included all Items and no subsequent claim for any additional Items will be entertained. | F39: =IFERROR(E39*D39,0) -> 0
F40: =IFERROR(E40*D40,0) -> 0
F41: =IFERROR(E41*D41,0) -> 0
F42: =IFERROR(E42*D42,0) -> 0
F43: =IFERROR(E43*D43,0) -> 0
F44: =IFERROR(E44*D44,0) -> 0
F56: =IFERROR(E56*D56,0) -> 0
F57: =IFERROR(E57*D57,0) -> 0
F58: =IFERROR(E58*D58,0) -> 0
F59: =IFERROR(E59*D59,0) -> 0
F60: =IFERROR(E60*D60,0) -> 0
F61: =IFERROR(E61*D61,0) -> 0
F62: =IFERROR(E62*D62,0) -> 0
... F68: =IFERROR(E68*D68,0) -> 0
B69: Total Bill No. 1 Carried To Collection | F69: =SUM(F5:F68) -> 0
B70: BILL NO. 2 : SUB-STRUCTURE
A71: 2.01 | B71: Excavation for Foundation, UG Water tank, holding tanks, UG facilities, etc., starting from the excavation level of the Existing natural ground level up to bottom of foundation | F71: =IFERROR(E71*D71,0) -> 0
A72: a | B72: Excavation | C72: m3 | F72: =IFERROR(E72*D72,0) -> 0
A73: b | B73: Shoring Works (If Required) | C73: m | F73: =IFERROR(E73*D73,0) -> 0
A74: c | B74: Dewatering Works | C74: LS | F74: =IFERROR(E74*D74,0) -> 0
A75: 2.02 | B75: Remove surplus excavated materials from the site | C75: L.S. | F75: =IFERROR(E75*D75,0) -> 0
B76: Piling Works | F76: =IFERROR(E76*D76,0) -> 0
A77: a | B77: Pilling Work | C77: LS | F77: =IFERROR(E77*D77,0) -> 0
A78: b | B78: All pilling tests as per spec. | C78: LS | F78: =IFERROR(E78*D78,0) -> 0
A79: c | B79: Cutting of piles head | C79: LS | F79: =IFERROR(E79*D79,0) -> 0
A80: d | B80: Treatment and water proofing for all piles | C80: LS | F80: =IFERROR(E80*D80,0) -> 0
A81: 2.03 | B81: Supply & Provide RCC for Pile Caps Including Form Work, Steel Reinforcement and Necessary Items as Per Specifications & Engineer Approval | C81: m3 | F81: =IFERROR(E81*D81,0) -> 0
A82: 2.04 | B82: Supply & Provide RCC for Strap Beams Including Form Work, Steel Reinforcement and Necessary Items as Per Specifications & Engineer Approval | C82: m3 | F82: =IFERROR(E82*D82,0) -> 0
A83: 2.05 | B83: Supply & Provide RCC for Neck Columns and Neck Walls Including Form Work, Steel Reinforcement and Necessary Items as Per Specifications & Engineer Approval | C83: m3 | F83: =IFERROR(E83*D83,0) -> 0
A84: 2.06 | B84: Refilling with Approved result of excavation, or Imported Back Fill (up to tie beam level) as directed by the Engineer | C84: m3 | F84: =IFERROR(E84*D84,0) -> 0
A85: 2.07 | B85: Supply & Provide Road Base Compacted as per Structural Drawings, up to 97% as per standards, spec. soil report and Structural Drawings. | C85: m3 | F85: =IFERROR(E85*D85,0) -> 0
A86: 2.08 | B86: Supply & Provide Anti-termite Treatment as Per Specifications & Engineer Approval | C86: m2 | F86: =IFERROR(E86*D86,0) -> 0
A87: 2.09 | B87: Supply & Provide 1000 G Polythene Sheets as Per Specifications, Structure Drawings & Engineer Approval | C87: m2 | F87: =IFERROR(E87*D87,0) -> 0
A88: 2.1 | B88: Supply & Provide Blinding Concrete ; 100 mm thick under Foundation, UG Water Tank, etc. as Per Specifications, Structure Drawings & Engineer Approval | C88: m3 | F88: =IFERROR(E88*D88,0) -> 0
A89: 2.11 | B89: Supply & Provide RCC for Tie Beams Including Form Work, Steel Reinforcement and Necessary Items as Per Specifications & Engineer Approval | C89: m3 | F89: =IFERROR(E89*D89,0) -> 0
A90: 2.12 | B90: Supply & Provide RCC for Neck Walls Including Form Work, Steel Reinforcement and Necessary Items as Per Specifications & Engineer Approval | C90: m3 | F90: =IFERROR(E90*D90,0) -> 0
A91: 2.13 | B91: Supply & Provide Waterproof RCC for all surfaces to the Under-Ground Water Tank, Water Proof Concrete Including Form Work, Steel Reinforcement and Necessary Items as Per Specifications & Engineer Approval | C91: m3 | F91: =IFERROR(E91*D91,0) -> 0
A92: 2.14 | B92: Supply & Provide RCC Slab On Grade ( SOG/ Slab on Ground ) with BRC mesh A252 or as indicated in the Structural Drawings above 95% Well Compacted Soil, and 1000 g Polyethylene Sheet. Including Form Work, Steel Reinforcement and Necessary Items as Per Specifications & Engineer Approval | C92: m3 | F92: =IFERROR(E92*D92,0) -> 0
A93: 2.15 | B93: Supply & Apply SBS Water Proofing Membrane for Sub-structure works (Pile Caps, Strap Beams, Ground beam, Retaining Walls, Water tank external surface, etc. ), as Per Specifications, Structure Drawings & Engineer Approval | F93: =IFERROR(E93*D93,0) -> 0
A94: a | B94: Horizontal Surfaces: One-layer 4mm SBS Water Proofing Membrane + Protection Screed as per specifications | C94: m2 | F94: =IFERROR(E94*D94,0) -> 0
A95: b | B95: Vertical Surfaces: One-layer 4mm SBS Water Proofing Membrane + Protection Board as per specifications | C95: m2 | F95: =IFERROR(E95*D95,0) -> 0
A96: 2.16 | B96: Supply & Apply GRP Waterproofing lining for Internal Surfaces of Under Ground Water Tank as Per Specifications & Engineer Approval | C96: m2 | F96: =IFERROR(E96*D96,0) -> 0
A97: 2.17 | B97: Damp proof Course (DPC) BituSeal 1000 self-adhesive, first line for block works at ground floor and around all wet areas (Kitchens, baths, toilets, Balconies for all floors) | C97: RM | F97: =IFERROR(E97*D97,0) -> 0
A98: 2.18 | B98: Supply & Apply 2 Coats Of Acrylic, Cementitious Waterproof, for Internal Surfaces of Manholes as per Specifications and Engineer's Approval | C98: m2 | F98: =IFERROR(E98*D98,0) -> 0
A99: 2.19 | B99: Supply & Apply Substructure solid block Under External Tie Beams including all necessary Items As per Specifications, Drawings & Engineer Approval | C99: m2 | F99: =IFERROR(E99*D99,0) -> 0
B100: Additional Items: The contractor to detail below any additional Items (with quantities and rates) shown in the drawings, mentioned in the specs. And /or required for satisfactory completion of the buildup of the lump sum project price of this section of works. Should the contractor fail to insert any Item in this section, it will be deemed that his lump sum price for the entire project included all Items and no subsequent claim for any additional Items will be entertained. | F100: =IFERROR(E100*D100,0) -> 0
F101: =IFERROR(E101*D101,0) -> 0
F102: =IFERROR(E102*D102,0) -> 0
F103: =IFERROR(E103*D103,0) -> 0
F104: =IFERROR(E104*D104,0) -> 0
F105: =IFERROR(E105*D105,0) -> 0
F106: =IFERROR(E106*D106,0) -> 0
F107: =IFERROR(E107*D107,0) -> 0
F108: =IFERROR(E108*D108,0) -> 0
B109: Total Bill No. 2 Carried To Collection | F109: =SUM(F71:F108) -> 0
B110: BILL NO. 3 : SUPER-STRUCTURE
A111: 3.01 | B111: Supply & Provide RCC for Columns, Walls, Core & Shear walls Including Form Work, Steel Reinforcement and Necessary Items as Per Specifications, Structure Drawings & Engineer Approval | C111: m3 | F111: =IFERROR(E111*D111,0) -> 0
A112: 3.02 | B112: Supply & Provide RCC for Beams Including Form Work, Steel Reinforcement and Necessary Items as Per Specifications, Structure Drawings & Engineer Approval | C112: m3 | F112: =IFERROR(E112*D112,0) -> 0
A113: 3.03 | B113: Supply & Provide RCC for Slabs Including Form Work, Steel Reinforcement and Necessary Items as Per Specifications, Structure Drawings & Engineer Approval | C113: m3 | F113: =IFERROR(E113*D113,0) -> 0
A114: 3.04 | B114: Supply & Provide RCC for Post-tension Slabs Including Form Work, Steel Reinforcement and Necessary Items as per Specifications, Structure Drawings & Engineer Approval | C114: m3 | F114: =IFERROR(E114*D114,0) -> 0
A115: 3.05 | B115: Supply & Provide RCC for Parking Ramps Including Form Work, Steel Reinforcement and Necessary Items as Per Specifications, Structure Drawings & Engineer Approval | C115: m3 | F115: =IFERROR(E115*D115,0) -> 0
A116: 3.06 | B116: Supply & Provide RCC for Stair Slabs & Flights Including Form Work, Steel Reinforcement and Necessary Items as Per Specifications, Structure Drawings & Engineer Approval | C116: m3 | F116: =IFERROR(E116*D116,0) -> 0
A117: 3.07 | B117: Supply & Provide RCC for Parapets Including Form Work, Steel Reinforcement and Necessary Items as Per Specifications, Structure Drawings & Engineer Approval | C117: m3 | F117: =IFERROR(E117*D117,0) -> 0
A118: 3.08 | B118: Supply & Provide RCC for Upstands Including Form Work, Steel Reinforcement and Necessary Items as Per Specifications, Structure Drawings & Engineer Approval | C118: m3 | F118: =IFERROR(E118*D118,0) -> 0
A119: 3.09 | B119: Supply & Provide RCC for Lintels/arches/etc. Including Form Work, Steel Reinforcement and Necessary Items as Per Specifications & Engineer Approval | C119: m3 | F119: =IFERROR(E119*D119,0) -> 0
A120: 3.1 | B120: Supply & Provide RCC for Entrance Steps and Ramps Including Form Work, Steel Reinforcement and Necessary Items as Per Specifications, Structure Drawings & Engineer Approval | C120: m3 | F120: =IFERROR(E120*D120,0) -> 0
A121: 3.11 | B121: Supply & Provide RCC for Trench Including Form Work, Steel Reinforcement and Necessary Items as Per Specifications & Engineer Approval | C121: m3 | F121: =IFERROR(E121*D121,0) -> 0
A122: 3.12 | B122: Supply & Provide RCC for Transfer Beams & Slab Including Form Work, Steel Reinforcement and Necessary Items as Per Specifications & Engineer Approval | C122: m3 | F122: =IFERROR(E122*D122,0) -> 0
... A125: 3.15 | B125: Supply & Provide 10 cm high RCC slabs for Block Works Nich as indicated on Arch drawings. | C125: m3 | F125: =IFERROR(E125*D125,0) -> 0
B126: Additional Items: The contractor to detail below any additional Items (with quantities and rates) shown in the drawings, mentioned in the specs. And /or required for satisfactory completion of the buildup of the lump sum project price of this section of works. Should the contractor fail to insert any Item in this section, it will be deemed that his lump sum price for the entire project included all Items and no subsequent claim for any additional Items will be entertained. | F126: =IFERROR(E126*D126,0) -> 0
F127: =IFERROR(E127*D127,0) -> 0
F128: =IFERROR(E128*D128,0) -> 0
F129: =IFERROR(E129*D129,0) -> 0
F130: =IFERROR(E130*D130,0) -> 0
F131: =IFERROR(E131*D131,0) -> 0
F132: =IFERROR(E132*D132,0) -> 0
F133: =IFERROR(E133*D133,0) -> 0
F134: =IFERROR(E134*D134,0) -> 0
F135: =IFERROR(E135*D135,0) -> 0
F136: =IFERROR(E136*D136,0) -> 0
F137: =IFERROR(E137*D137,0) -> 0
F138: =IFERROR(E138*D138,0) -> 0
... F147: =IFERROR(E147*D147,0) -> 0
B148: Total Bill No. 3 Carried To Collection | F148: =SUM(F111:F147) -> 0
...

Sheet SUMMARY
A1: COLLECTION OF BILLS No. 1 to 14 : SUMMARY PAGE
A2: 1 | B2: PRELIMINARIES | F2: ='BILL 1 TO 14'!F69 -> 0
A3: 2 | B3: SUB-STRUCTURE | F3: ='BILL 1 TO 14'!F109 -> 0
A4: 3 | B4: SUPER-STRUCTURE | F4: ='BILL 1 TO 14'!F148 -> 0
A5: 4 | B5: BLOCKWORK | F5: ='BILL 1 TO 14'!F170 -> 0
A6: 5 | B6: WATERPROOFING WORKS | F6: ='BILL 1 TO 14'!F193 -> 0
A7: 6 | B7: CARPENTRY& JOINERY WORKS | F7: ='BILL 1 TO 14'!F232 -> 0
A8: 7 | B8: METAL & GLAZING WORKS | F8: ='BILL 1 TO 14'!F306 -> 0
A9: 8 | B9: FINISHING WORKS | F9: ='BILL 1 TO 14'!F361 -> 0
A10: 9 | B10: MECHANICAL WORKS | F10: ='BILL 1 TO 14'!F511 -> 0
A11: 10 | B11: ELECTRICAL SYSTEM | F11: ='BILL 1 TO 14'!F662 -> 0
A12: 11 | B12: NATURAL GAS SYSTEM | F12: ='BILL 1 TO 14'!F688 -> 0
A13: 12 | B13: EXTERNAL WORKS | F13: ='BILL 1 TO 14'!F705 -> 0
A14: 13 | B14: FITTING, FIXTURES & EQUIPMENT | F14: ='BILL 1 TO 14'!F721 -> 0
A15: 14 | B15: PROVISIONAL SUMS | F15: ='BILL 1 TO 14'!F751 -> 1440000
A16: SUB-TOTAL (Before Discount) | F16: =SUM(F2:F15) -> 1440000
A17: Tenderer's Price Adjustment, Discount (%)
A18: GRAND TOTAL PROJECT PRICE (AED) | F18: =SUM(F16:F17) -> 1440000
B20: TOTAL AMOUNT IN WORDS
B21: Dhs…...............................................................................................................................................
B22: …...…...........................................................................................................................................
B24: SIGNATURE OF TENDERER STAMP OF TENDERER
